pycounts_tat25/__init__.py
pycounts_tat25/plotting.py
pycounts_tat25/pycounts_tat25.py
pycounts_tat25-0.1.0.dist-info/LICENSE
pycounts_tat25-0.1.0.dist-info/METADATA
pycounts_tat25-0.1.0.dist-info/WHEEL
pycounts_tat25-0.1.0.dist-info/RECORD
